ansiblepack/__init__.py
ansiblepack/_version.py
ansiblepack/cli.py
ansiblepack/pack.py
ansiblepack/py.typed
ansiblepack/salt/_modules/ansiblepack.py
ansiblepack/salt/_proxy/ansiblepack.py
ansiblepack/salt/_states/ansiblepack.py
ansiblepack/salt/_utils/ansiblepack.py
ansiblepack/utils/__init__.py
ansiblepack/utils/pack.py
ansiblepack/utils/process.py
ansiblepack-0.0.1.dist-info/METADATA
ansiblepack-0.0.1.dist-info/WHEEL
ansiblepack-0.0.1.dist-info/entry_points.txt
ansiblepack-0.0.1.dist-info/licenses/LICENSE
ansiblepack-0.0.1.dist-info/RECORD
