Metadata-Version: 2.4
Name: ansiblepack
Version: 0.0.1
Summary: Self contained ansible builtin and collection modules.
Project-URL: Documentation, https://github.com/cheburakshu/ansible-pack#readme
Project-URL: Issues, https://github.com/cheburakshu/ansible-pack/issues
Project-URL: Source, https://github.com/cheburakshu/ansible-pack
Author-email: cheburakshu <cheburakshu@gmail.com>
License-Expression: GPL-3.0-or-later
License-File: LICENSE
Classifier: Development Status :: 4 - Beta
Classifier: Programming Language :: Python
Classifier: Programming Language :: Python :: 3.10
Classifier: Programming Language :: Python :: 3.11
Classifier: Programming Language :: Python :: 3.12
Classifier: Programming Language :: Python :: Implementation :: CPython
Classifier: Programming Language :: Python :: Implementation :: PyPy
Requires-Python: >=3.10
Requires-Dist: ansiblecall
